open_skills/Dockerfile
open_skills/__init__.py
open_skills/cli.py
open_skills/sandbox.py
open_skills_mcp-0.2.3.dist-info/METADATA
open_skills_mcp-0.2.3.dist-info/WHEEL
open_skills_mcp-0.2.3.dist-info/entry_points.txt
open_skills_mcp-0.2.3.dist-info/licenses/LICENSE
open_skills_mcp-0.2.3.dist-info/RECORD
