Metadata-Version: 2.4
Name: open-skills-mcp
Version: 0.2.3
Summary: A universal MCP skill runtime executing in a secure Docker sandbox.
License-File: LICENSE
Requires-Python: >=3.10
Requires-Dist: boto3
Requires-Dist: docker
Requires-Dist: mcp[cli]
Requires-Dist: python-dotenv
Requires-Dist: pyyaml
Requires-Dist: requests
